{
    "補習班代碼": "21201007080001",
    "主管機關文件單位代碼": "99108",
    "補習班名稱": "私立文盛文理語文珠心算短期補習班",
    "補習班英文名稱": "Private Short-Term Busiban",
    "補習班類別\/科目": "文理類,外語類,商類：珠算、心算、會計,",
    "地址": "鶯歌區鳳鳴路13、19、21號(1、2樓)(因門牌整編)",
    "英文地址": "",
    "電話": "(02)26782678",
    "立案情形": "已立案",
    "電話網類別": "",
    "電話網層別": "X-X-X",
    "立案文號": "府教社字第0990546426號",
    "廢止、註銷文號": "",
    "立案日期": "2010-10-28",
    "廢止、註銷日期": "",
    "傳真號碼": "(02)",
    "電子郵件": "",
    "教室數": "9間",
    "飲用水設備維護管理": "",
    "教室面積": "125.43 平方公尺",
    "班舍總面積": "236.01平方公尺",
    "暫停招生文號": "",
    "暫停招生生效日": "",
    "暫停招生截止日": "",
    "負責人": [
        "陳瑞勝"
    ],
    "設立人": [
        "陳瑞勝"
    ],
    "班主任": [
        "鍾玉美"
    ],
    "核准科目": [
        {
            "核准科目名稱": "珠心算",
            "核准班級數": "2班",
            "每班核准人數": "13人",
            "每週總節(時)數": "12",
            "修業期限": "3個月",
            "招生對象": "(不限年齡)"
        },
        {
            "核准科目名稱": "語文(英文)",
            "核准班級數": "4班",
            "每班核准人數": "17人",
            "每週總節(時)數": "56",
            "修業期限": "3個月",
            "招生對象": "(不限年齡)"
        },
        {
            "核准科目名稱": "文理(自然與生活科技)",
            "核准班級數": "4班",
            "每班核准人數": "17人",
            "每週總節(時)數": "48",
            "修業期限": "3個月",
            "招生對象": "國小、國中"
        }
    ],
    "職員工": [
        "涂美瑛",
        "廖涓伶",
        "簡秀菊",
        "朱景雲",
        "李敏華",
        "陳忠緯",
        "黃靜宜",
        "鍾玉美"
    ]
}