{
    "補習班代碼": "21200405200001",
    "主管機關文件單位代碼": "93144",
    "補習班名稱": "私立陽光森林文教股份有限公司台北縣分公司附設楊光森林語文短期補習班",
    "補習班英文名稱": "Private Short-Term Busiban",
    "補習班類別\/科目": "外語類,",
    "地址": "板橋區三民路2段215、217、219號3樓",
    "英文地址": "3F., No.215, Sec. 2, Sanmin Rd., Banciao City, Taipei County 220, Taiwan (R.O.C.)",
    "電話": "(02)29555576",
    "立案情形": "已立案",
    "電話網類別": "",
    "電話網層別": "X-X-X",
    "立案文號": "府教社字第 0930385816號",
    "廢止、註銷文號": "",
    "立案日期": "2004-05-28",
    "廢止、註銷日期": "",
    "傳真號碼": "(02)29555276",
    "電子郵件": "sunshinesanmin@yahoo.com.tw",
    "教室數": "2間",
    "飲用水設備維護管理": "",
    "教室面積": "70.75 平方公尺",
    "班舍總面積": "181.47平方公尺",
    "暫停招生文號": "府教社字第 號",
    "暫停招生生效日": "",
    "暫停招生截止日": "",
    "負責人": [
        "呂麗華"
    ],
    "設立人": [
        "呂麗華"
    ],
    "班主任": [
        "沈秀慧"
    ],
    "核准科目": [
        {
            "核准科目名稱": "美語",
            "核准班級數": "4班",
            "每班核准人數": "116人",
            "每週總節(時)數": "112",
            "修業期限": "6個月",
            "招生對象": "不限年齡"
        }
    ],
    "職員工": []
}