{
    "補習班代碼": "21200401120001",
    "主管機關文件單位代碼": "93017",
    "補習班名稱": "私立詮能文理短期補習班",
    "補習班英文名稱": "Private Short-Term Busiban",
    "補習班類別\/科目": "文理類,商類：珠算、心算、會計,",
    "地址": "新店區三民路71號1樓、75巷1弄3號1樓",
    "英文地址": "",
    "電話": "(02)29175252",
    "立案情形": "已立案",
    "電話網類別": "",
    "電話網層別": "X-X-X",
    "立案文號": "府教社字第0930017035號",
    "廢止、註銷文號": "",
    "立案日期": "2004-01-13",
    "廢止、註銷日期": "",
    "傳真號碼": "(02)8911-0862",
    "電子郵件": "evelyne0920@yahoo.com.tw",
    "教室數": "2間",
    "飲用水設備維護管理": "",
    "教室面積": "36.0 平方公尺",
    "班舍總面積": "84.11平方公尺",
    "暫停招生文號": "府教社字第 號",
    "暫停招生生效日": "",
    "暫停招生截止日": "",
    "負責人": [
        "陳敏玲"
    ],
    "設立人": [
        "陳敏玲"
    ],
    "班主任": [
        "陳敏玲"
    ],
    "核准科目": [
        {
            "核准科目名稱": "文理(自然)2班",
            "核准班級數": "2班",
            "每班核准人數": "30人",
            "每週總節(時)數": "8",
            "修業期限": "3個月",
            "招生對象": "國中"
        }
    ],
    "職員工": [
        "李和家"
    ]
}