{
    "補習班代碼": "21200912100002",
    "主管機關文件單位代碼": "98200",
    "補習班名稱": "私立育豪資優文理語文短期補習班",
    "補習班英文名稱": "Private Short-Term Busiban",
    "補習班類別\/科目": "文理類,外語類,",
    "地址": "板橋區中山路1段293之1號3樓",
    "英文地址": "",
    "電話": "(02)29549996",
    "立案情形": "已立案",
    "電話網類別": "",
    "電話網層別": "X-X-X",
    "立案文號": "府教社字第0980966931號",
    "廢止、註銷文號": "",
    "立案日期": "2009-12-04",
    "廢止、註銷日期": "",
    "傳真號碼": "(02)",
    "電子郵件": "",
    "教室數": "5間",
    "飲用水設備維護管理": "",
    "教室面積": "350.028 平方公尺",
    "班舍總面積": "499.87平方公尺",
    "暫停招生文號": "",
    "暫停招生生效日": "",
    "暫停招生截止日": "",
    "負責人": [
        "許文宗"
    ],
    "設立人": [
        "許文宗"
    ],
    "班主任": [
        "許文宗"
    ],
    "核准科目": [
        {
            "核准科目名稱": "語文",
            "核准班級數": "2班",
            "每班核准人數": "96人",
            "每週總節(時)數": "30",
            "修業期限": "3個月",
            "招生對象": "其他"
        },
        {
            "核准科目名稱": "自然、數學、國文、英語",
            "核准班級數": "2班",
            "每班核准人數": "96人",
            "每週總節(時)數": "70",
            "修業期限": "3個月",
            "招生對象": "其他"
        }
    ],
    "職員工": [
        "許惠心",
        "許惠心",
        "胡益鳴",
        "王秋媛",
        "羅弘軒",
        "葉文鈴",
        "王能邦",
        "鄭景穗",
        "黃國富",
        "林冠綸",
        "林品妤",
        "林品妤",
        "林奕蓁",
        "何佩蓉"
    ]
}