{
    "補習班代碼": "21201904250002",
    "主管機關文件單位代碼": "108022",
    "補習班名稱": "私立學悟處一對一重慶教室文理短期補習班",
    "補習班英文名稱": "Private Short-Term Busiban",
    "補習班類別\/科目": "文理類,",
    "地址": "板橋區重慶路250號2樓(含2、3、4樓)",
    "英文地址": "",
    "電話": "(02)2961-5101",
    "立案情形": "已立案",
    "電話網類別": "",
    "電話網層別": "X-X-X",
    "立案文號": "府教社字第1080555334號",
    "廢止、註銷文號": "",
    "立案日期": "2019-04-25",
    "廢止、註銷日期": "",
    "傳真號碼": "(02)",
    "電子郵件": "",
    "教室數": "6間",
    "飲用水設備維護管理": "",
    "教室面積": "152.44 平方公尺",
    "班舍總面積": "253.44平方公尺",
    "暫停招生文號": "",
    "暫停招生生效日": "",
    "暫停招生截止日": "",
    "負責人": [
        "許肇揚"
    ],
    "設立人": [
        "許肇揚"
    ],
    "班主任": [
        "郭忠豪"
    ],
    "核准科目": [
        {
            "核准科目名稱": "文理(英語、數學、理化)",
            "核准班級數": "4班",
            "每班核准人數": "28人",
            "每週總節(時)數": "60",
            "修業期限": "3個月",
            "招生對象": "不限年齡(A班23人、B班28人、C班28人、D班13人)"
        }
    ],
    "職員工": []
}