{
    "補習班代碼": "53200411170002",
    "主管機關文件單位代碼": "00168",
    "補習班名稱": "私立日光藝術教育空間美術短期補習班",
    "補習班英文名稱": "Private Short-Term Busiban",
    "補習班類別\/科目": "美術、書法、攝影、美工設計、圍棋類,",
    "地址": "嘉義縣民雄鄉西安村二十鄰進興街58號一樓",
    "英文地址": "1F., No.58, Jinsing St., Minsyong Township, Chiayi County 621, Taiwan (R.O.C.)",
    "電話": "(05)2268066 \/ 0952534230",
    "立案情形": "已立案",
    "電話網類別": "",
    "電話網層別": "X-X-X",
    "立案文號": "府教社字第0930142773 號",
    "廢止、註銷文號": "",
    "立案日期": "2004-11-17",
    "廢止、註銷日期": "",
    "傳真號碼": "(05)",
    "電子郵件": "sun.arts@gmail.com",
    "教室數": "1間",
    "飲用水設備維護管理": "學生自行準備飲用水",
    "教室面積": "151.65 平方公尺",
    "班舍總面積": "151.65平方公尺",
    "暫停招生文號": "府教社字第 號",
    "暫停招生生效日": "",
    "暫停招生截止日": "",
    "負責人": [
        "何晃岳"
    ],
    "設立人": [
        "何晃岳"
    ],
    "班主任": [
        "何晃岳"
    ],
    "核准科目": [
        {
            "核准科目名稱": "美術",
            "核准班級數": "4班",
            "每班核准人數": "20人",
            "每週總節(時)數": "8",
            "修業期限": "3個月",
            "招生對象": "國小"
        }
    ],
    "職員工": []
}