{
    "補習班代碼": "37200808150001",
    "主管機關文件單位代碼": "332",
    "補習班名稱": "苗栗縣私立典優文理短期補習班",
    "補習班英文名稱": "Private Short-Term Busiban",
    "補習班類別\/科目": "文理類,",
    "地址": "苗栗縣苑裡鎮客庄里信義路6之5號1F",
    "英文地址": "",
    "電話": "(037)854779",
    "立案情形": "已立案",
    "電話網類別": "",
    "電話網層別": "X-X-X",
    "立案文號": "府教社字第B1000264209號",
    "廢止、註銷文號": "",
    "立案日期": "2011-12-29",
    "廢止、註銷日期": "",
    "傳真號碼": "(037)",
    "電子郵件": "",
    "教室數": "1間",
    "飲用水設備維護管理": "",
    "教室面積": "47.33 平方公尺",
    "班舍總面積": "47.33平方公尺",
    "暫停招生文號": "",
    "暫停招生生效日": "",
    "暫停招生截止日": "",
    "負責人": [
        "李莉禎"
    ],
    "設立人": [
        "李莉禎"
    ],
    "班主任": [
        "李莉禎"
    ],
    "核准科目": [
        {
            "核准科目名稱": "數學",
            "核准班級數": "1班",
            "每班核准人數": "20人",
            "每週總節(時)數": "6",
            "修業期限": "4個月",
            "招生對象": "國中"
        },
        {
            "核准科目名稱": "英文",
            "核准班級數": "1班",
            "每班核准人數": "20人",
            "每週總節(時)數": "15",
            "修業期限": "4個月",
            "招生對象": "國中"
        }
    ],
    "職員工": []
}