{
    "補習班代碼": "42200508109001",
    "主管機關文件單位代碼": "1601",
    "補習班名稱": "朝陽富元教育股份有限公司附設臺中市私立朝揚文理短期補習班",
    "補習班英文名稱": "Private   niou    yue        Foreign  Languages        Short-Term Busiban",
    "補習班類別\/科目": "文理類,外語類,",
    "地址": "臺中市大里區立新二街13號2-3樓",
    "英文地址": "2-3F., No.13, Lixin 2nd St., Dali City, Taichung County 412, Taiwan (R.O.C.)",
    "電話": "(04)22750609",
    "立案情形": "已立案",
    "電話網類別": "",
    "電話網層別": "X-X-X",
    "立案文號": "府教社字第0940207750 號",
    "廢止、註銷文號": "",
    "立案日期": "2005-08-02",
    "廢止、註銷日期": "",
    "傳真號碼": "(04)",
    "電子郵件": "",
    "教室數": "3間",
    "飲用水設備維護管理": "",
    "教室面積": "109.564 平方公尺",
    "班舍總面積": "223.18平方公尺",
    "暫停招生文號": "府教社字第 號",
    "暫停招生生效日": "",
    "暫停招生截止日": "",
    "負責人": [
        "鄭一鳴"
    ],
    "設立人": [
        "朝陽富元教育股份有限公司(代表人鄭一鳴)"
    ],
    "班主任": [
        "吳國禎"
    ],
    "核准科目": [
        {
            "核准科目名稱": "美語",
            "核准班級數": "23班",
            "每班核准人數": "15人",
            "每週總節(時)數": "2",
            "修業期限": "3個月",
            "招生對象": "國小"
        },
        {
            "核准科目名稱": "英文",
            "核准班級數": "13班",
            "每班核准人數": "15人",
            "每週總節(時)數": "2",
            "修業期限": "3個月",
            "招生對象": "國中"
        },
        {
            "核准科目名稱": "數學A班",
            "核准班級數": "18班",
            "每班核准人數": "15人",
            "每週總節(時)數": "2",
            "修業期限": "3個月",
            "招生對象": "國小"
        },
        {
            "核准科目名稱": "數學B班",
            "核准班級數": "9班",
            "每班核准人數": "15人",
            "每週總節(時)數": "2",
            "修業期限": "3個月",
            "招生對象": "國中"
        }
    ],
    "職員工": [
        "蕭漢茗",
        "葉金鳳",
        "張育誠",
        "陳姿均",
        "賴盈蓁"
    ]
}