{
    "補習班代碼": "42200207319146",
    "主管機關文件單位代碼": "a412018",
    "補習班名稱": "智海文教事業有限公司附設臺中市私立成功文理補習班",
    "補習班英文名稱": "Private YEN LAO SHIH  Liberal  Arts\/Science  Program    Short-Term  Busiban",
    "補習班類別\/科目": "文理類,",
    "地址": "臺中市大里區向學一路3號1-4樓",
    "英文地址": "1-4F,No.3, Siangsyue 1st Rd., Dali City, Taichung County 412, Taiwan (R.O.C.)",
    "電話": "0424916266",
    "立案情形": "已立案",
    "電話網類別": "",
    "電話網層別": "",
    "立案文號": "府教社字第203795號",
    "廢止、註銷文號": "",
    "立案日期": "1996-08-14",
    "廢止、註銷日期": "",
    "傳真號碼": "0424916268",
    "電子郵件": "",
    "教室數": "3間",
    "飲用水設備維護管理": "外接式飲水機",
    "教室面積": "86.71 平方公尺",
    "班舍總面積": "189.72平方公尺",
    "暫停招生文號": "",
    "暫停招生生效日": "",
    "暫停招生截止日": "",
    "負責人": [
        "智海文教事業有限公司 代表人:陳宏諭"
    ],
    "設立人": [
        "智海文教事業有限公司 代表人:陳宏諭"
    ],
    "班主任": [
        "陳惠珍"
    ],
    "核准科目": [
        {
            "核准科目名稱": "數學",
            "核准班級數": "1班",
            "每班核准人數": "20人",
            "每週總節(時)數": "6",
            "修業期限": "6個月",
            "招生對象": "國中"
        },
        {
            "核准科目名稱": "英文",
            "核准班級數": "1班",
            "每班核准人數": "20人",
            "每週總節(時)數": "6",
            "修業期限": "6個月",
            "招生對象": "國中"
        },
        {
            "核准科目名稱": "理化",
            "核准班級數": "1班",
            "每班核准人數": "20人",
            "每週總節(時)數": "6",
            "修業期限": "6個月",
            "招生對象": "國中"
        }
    ],
    "職員工": [
        "田為安",
        "林泰夆",
        "陳珊妤",
        "黃群祐",
        "黃皓群",
        "廖宸寬",
        "蘇振瑋",
        "李怡安"
    ]
}