{
    "補習班代碼": "42200207319581",
    "主管機關文件單位代碼": "b428001",
    "補習班名稱": "臺中市私立傑弗遜美語短期補習班",
    "補習班英文名稱": "Private   CHIEH FO HSUN      Foreign  Languages   Short-Term  Busiban",
    "補習班類別\/科目": "外語類,",
    "地址": "臺中市大雅區雅潭路4段728號、730號1-4樓",
    "英文地址": "1-4F., No.320, No.322 , Yatan Rd., Tanzih Township, Taichung County 427, Taiwan (R.O.C.)",
    "電話": "04-25685094",
    "立案情形": "已立案",
    "電話網類別": "",
    "電話網層別": "",
    "立案文號": "214227",
    "廢止、註銷文號": "",
    "立案日期": "1995-09-08",
    "廢止、註銷日期": "",
    "傳真號碼": "",
    "電子郵件": "",
    "教室數": "3間",
    "飲用水設備維護管理": "",
    "教室面積": "162.15 平方公尺",
    "班舍總面積": "231.0平方公尺",
    "暫停招生文號": "",
    "暫停招生生效日": "",
    "暫停招生截止日": "",
    "負責人": [
        "李怡婷"
    ],
    "設立人": [
        "李怡婷"
    ],
    "班主任": [
        "李怡婷"
    ],
    "核准科目": [
        {
            "核准科目名稱": "英文",
            "核准班級數": "1班",
            "每班核准人數": "20人",
            "每週總節(時)數": "3",
            "修業期限": "6個月",
            "招生對象": "國小"
        },
        {
            "核准科目名稱": "英文",
            "核准班級數": "1班",
            "每班核准人數": "20人",
            "每週總節(時)數": "3",
            "修業期限": "6個月",
            "招生對象": "國中"
        },
        {
            "核准科目名稱": "英文",
            "核准班級數": "1班",
            "每班核准人數": "20人",
            "每週總節(時)數": "3",
            "修業期限": "3個月",
            "招生對象": "國小"
        }
    ],
    "職員工": [
        "李怡婷",
        "黃小伶",
        "黃以嫻",
        "王新智"
    ]
}