{
    "補習班代碼": "42200410280001",
    "主管機關文件單位代碼": "",
    "補習班名稱": "臺中市私立柏翔電腦附設美語短期補習班",
    "補習班英文名稱": "Private BO SIANG Computer\/ English Language Short-Term Busiban",
    "補習班類別\/科目": "外語類,資訊類,",
    "地址": "臺中市北屯區陳平路89號1-3樓",
    "英文地址": "1-3F., No.89, Chenping Rd., Beitun District, Taichung City 406",
    "電話": "(04)22918003",
    "立案情形": "已立案",
    "電話網類別": "",
    "電話網層別": "",
    "立案文號": "府教社字第0930215605 號",
    "廢止、註銷文號": "",
    "立案日期": "2004-12-24",
    "廢止、註銷日期": "",
    "傳真號碼": "(04)",
    "電子郵件": "",
    "教室數": "4間",
    "飲用水設備維護管理": "外接式飲水機",
    "教室面積": "72.28 平方公尺",
    "班舍總面積": "150.531平方公尺",
    "暫停招生文號": "",
    "暫停招生生效日": "",
    "暫停招生截止日": "",
    "負責人": [
        "伍嘉雄"
    ],
    "設立人": [
        "伍嘉雄"
    ],
    "班主任": [
        "王怡筠"
    ],
    "核准科目": [
        {
            "核准科目名稱": "美語",
            "核准班級數": "3班",
            "每班核准人數": "21人",
            "每週總節(時)數": "6",
            "修業期限": "3個月",
            "招生對象": "國小"
        },
        {
            "核准科目名稱": "電腦",
            "核准班級數": "2班",
            "每班核准人數": "11人",
            "每週總節(時)數": "6",
            "修業期限": "3個月",
            "招生對象": "國小"
        }
    ],
    "職員工": []
}