{
    "補習班代碼": "42201205140002",
    "主管機關文件單位代碼": "",
    "補習班名稱": "臺中市私立英博語文短期補習班",
    "補習班英文名稱": "Private Short-Term Busiban",
    "補習班類別\/科目": "外語類,",
    "地址": "臺中市南屯區大墩南路412-1號1-4樓，臺中市南屯區大墩南路408號1-4樓",
    "英文地址": "",
    "電話": "(04)24726068",
    "立案情形": "已立案",
    "電話網類別": "",
    "電話網層別": "",
    "立案文號": "中市教社字第1010036702 號",
    "廢止、註銷文號": "",
    "立案日期": "2012-05-30",
    "廢止、註銷日期": "",
    "傳真號碼": "(04)",
    "電子郵件": "tc14.shane@gmail.com",
    "教室數": "9間",
    "飲用水設備維護管理": "",
    "教室面積": "265.11 平方公尺",
    "班舍總面積": "611.62平方公尺",
    "暫停招生文號": "",
    "暫停招生生效日": "",
    "暫停招生截止日": "",
    "負責人": [
        "李玉珍"
    ],
    "設立人": [
        "李玉珍"
    ],
    "班主任": [
        "李玉珍"
    ],
    "核准科目": [
        {
            "核准科目名稱": "英語",
            "核准班級數": "1班",
            "每班核准人數": "49人",
            "每週總節(時)數": "15",
            "修業期限": "3個月",
            "招生對象": "國小"
        },
        {
            "核准科目名稱": "英語",
            "核准班級數": "1班",
            "每班核准人數": "49人",
            "每週總節(時)數": "15",
            "修業期限": "3個月",
            "招生對象": "國小"
        },
        {
            "核准科目名稱": "英語",
            "核准班級數": "1班",
            "每班核准人數": "46人",
            "每週總節(時)數": "15",
            "修業期限": "3個月",
            "招生對象": "國中"
        },
        {
            "核准科目名稱": "英語",
            "核准班級數": "1班",
            "每班核准人數": "22人",
            "每週總節(時)數": "15",
            "修業期限": "3個月",
            "招生對象": "國中"
        },
        {
            "核准科目名稱": "英語",
            "核准班級數": "1班",
            "每班核准人數": "21人",
            "每週總節(時)數": "15",
            "修業期限": "3個月",
            "招生對象": "高中"
        },
        {
            "核准科目名稱": "英語",
            "核准班級數": "1班",
            "每班核准人數": "24人",
            "每週總節(時)數": "15",
            "修業期限": "3個月",
            "招生對象": "國小"
        },
        {
            "核准科目名稱": "英語",
            "核准班級數": "1班",
            "每班核准人數": "21人",
            "每週總節(時)數": "15",
            "修業期限": "3個月",
            "招生對象": "高中"
        },
        {
            "核准科目名稱": "英語",
            "核准班級數": "1班",
            "每班核准人數": "24人",
            "每週總節(時)數": "15",
            "修業期限": "3個月",
            "招生對象": "國小"
        }
    ],
    "職員工": [
        "藍佩瑄",
        "黃珮瑄",
        "洪美慈",
        "蔡岳蓉",
        "朱妍蓁",
        "朱育萱",
        "楊千宜",
        "楊芷菱",
        "陳博雅",
        "吳侑庭",
        "謝婧辰",
        "童姿瑀",
        "林吟樺",
        "朱靜誼",
        "吳敏訰",
        "葉家瑄",
        "林准羽"
    ]
}