{
    "補習班代碼": "70200511150002",
    "主管機關文件單位代碼": "1156",
    "補習班名稱": "台灣知識庫股份有限公司附設大碩洋碩甄戰數位學堂文理短期補習班",
    "補習班英文名稱": "Private Shu Wei  Siyue Tang Liberal Arts\/Science Programs Short-Term Busiban of Taiwan Knowledge Base Co., Ltd.",
    "補習班類別\/科目": "文理類,",
    "地址": "楠梓區建楠路236號5樓、5樓之1",
    "英文地址": "5F &amp;amp;amp;amp;amp;amp; 5F-1., No.236, Jiannan Rd., Nanzih Dist.",
    "電話": "355-8783",
    "立案情形": "已立案",
    "電話網類別": "",
    "電話網層別": "",
    "立案文號": "教四字第0960001830號",
    "廢止、註銷文號": "",
    "立案日期": "2007-01-15",
    "廢止、註銷日期": "",
    "傳真號碼": "",
    "電子郵件": "angel@ksdaso.com.tw",
    "教室數": "3間",
    "飲用水設備維護管理": "",
    "教室面積": "229.4 平方公尺",
    "班舍總面積": "426.75平方公尺",
    "暫停招生文號": "",
    "暫停招生生效日": "",
    "暫停招生截止日": "",
    "負責人": [
        "邱昌其"
    ],
    "設立人": [
        "台灣知識庫股份有限公司（代表人：邱昌其）"
    ],
    "班主任": [
        "蕭雅鳳"
    ],
    "核准科目": [
        {
            "核准科目名稱": "升研究所",
            "核准班級數": "1班",
            "每班核准人數": "28人",
            "每週總節(時)數": "18",
            "修業期限": "4個月",
            "招生對象": "升四技二專大專"
        },
        {
            "核准科目名稱": "升大學",
            "核准班級數": "2班",
            "每班核准人數": "75人",
            "每週總節(時)數": "9",
            "修業期限": "4個月",
            "招生對象": "高中"
        }
    ],
    "職員工": []
}