{
    "補習班代碼": "70200204021023",
    "主管機關文件單位代碼": "198",
    "補習班名稱": "私立東昇文理短期補習班",
    "補習班英文名稱": "Private Dong Sheng Liberal Arts\/Science Programs Short-Term Busiban",
    "補習班類別\/科目": "文理類,",
    "地址": "小港區崇本街70號1-4樓",
    "英文地址": "No.70, Chongben St., Siaogang Dist.",
    "電話": "815-5878  \/  815-5879",
    "立案情形": "已立案",
    "電話網類別": "南文4",
    "電話網層別": "5\/3\/1",
    "立案文號": "教四字第33247號",
    "廢止、註銷文號": "",
    "立案日期": "1996-10-28",
    "廢止、註銷日期": "",
    "傳真號碼": "861-5013",
    "電子郵件": "wang0958657403@gmail.com",
    "教室數": "9間",
    "飲用水設備維護管理": "外接式飲水機",
    "教室面積": "269.0 平方公尺",
    "班舍總面積": "402.92平方公尺",
    "暫停招生文號": "",
    "暫停招生生效日": "",
    "暫停招生截止日": "",
    "負責人": [
        "簡茂寅"
    ],
    "設立人": [
        "簡茂寅"
    ],
    "班主任": [
        "簡茂寅"
    ],
    "核准科目": [
        {
            "核准科目名稱": "英文",
            "核准班級數": "1班",
            "每班核准人數": "26人",
            "每週總節(時)數": "2",
            "修業期限": "1個月",
            "招生對象": "國小"
        },
        {
            "核准科目名稱": "數學",
            "核准班級數": "1班",
            "每班核准人數": "26人",
            "每週總節(時)數": "2",
            "修業期限": "1個月",
            "招生對象": "國小"
        },
        {
            "核准科目名稱": "國文",
            "核准班級數": "1班",
            "每班核准人數": "22人",
            "每週總節(時)數": "2",
            "修業期限": "1個月",
            "招生對象": "國小"
        },
        {
            "核准科目名稱": "自然",
            "核准班級數": "1班",
            "每班核准人數": "22人",
            "每週總節(時)數": "2",
            "修業期限": "1個月",
            "招生對象": "國小"
        },
        {
            "核准科目名稱": "社會",
            "核准班級數": "1班",
            "每班核准人數": "15人",
            "每週總節(時)數": "2",
            "修業期限": "1個月",
            "招生對象": "國小"
        },
        {
            "核准科目名稱": "英文",
            "核准班級數": "1班",
            "每班核准人數": "22人",
            "每週總節(時)數": "2",
            "修業期限": "1個月",
            "招生對象": "國中"
        },
        {
            "核准科目名稱": "數學",
            "核准班級數": "1班",
            "每班核准人數": "17人",
            "每週總節(時)數": "2",
            "修業期限": "1個月",
            "招生對象": "國中"
        },
        {
            "核准科目名稱": "國文",
            "核准班級數": "1班",
            "每班核准人數": "26人",
            "每週總節(時)數": "2",
            "修業期限": "1個月",
            "招生對象": "國中"
        },
        {
            "核准科目名稱": "自然",
            "核准班級數": "1班",
            "每班核准人數": "10人",
            "每週總節(時)數": "2",
            "修業期限": "1個月",
            "招生對象": "國中"
        },
        {
            "核准科目名稱": "社會",
            "核准班級數": "1班",
            "每班核准人數": "17人",
            "每週總節(時)數": "2",
            "修業期限": "1個月",
            "招生對象": "國中"
        }
    ],
    "職員工": []
}