{
    "補習班代碼": "70201903080001",
    "主管機關文件單位代碼": "2098",
    "補習班名稱": "私立耶加文理短期補習班新民分班",
    "補習班英文名稱": "Private Ye Jia Liberal Arts\/Science Programs Short-Term Busiban Sinmin Branch",
    "補習班類別\/科目": "文理類,",
    "地址": "左營區文瑞路75號1-2樓",
    "英文地址": "1-23F., No. 75, Wenrui Rd., Zuoying Dist., Kaohsiung City 813, Taiwan (R.O.C.)",
    "電話": "345-4681",
    "立案情形": "已立案",
    "電話網類別": "",
    "電話網層別": "",
    "立案文號": "高市教社字第11030856700號",
    "廢止、註銷文號": "",
    "立案日期": "2021-02-22",
    "廢止、註銷日期": "",
    "傳真號碼": "",
    "電子郵件": "brianshen2001ca@gmail.com",
    "教室數": "1間",
    "飲用水設備維護管理": "外接式飲水機",
    "教室面積": "32.27 平方公尺",
    "班舍總面積": "112.17平方公尺",
    "暫停招生文號": "",
    "暫停招生生效日": "",
    "暫停招生截止日": "",
    "負責人": [
        "沈文麟"
    ],
    "設立人": [
        "沈文麟"
    ],
    "班主任": [
        "謝宛真"
    ],
    "核准科目": [
        {
            "核准科目名稱": "英文",
            "核准班級數": "3班",
            "每班核准人數": "20人",
            "每週總節(時)數": "12",
            "修業期限": "3個月",
            "招生對象": "國中"
        },
        {
            "核准科目名稱": "數學",
            "核准班級數": "1班",
            "每班核准人數": "20人",
            "每週總節(時)數": "4",
            "修業期限": "3個月",
            "招生對象": "國中"
        },
        {
            "核准科目名稱": "理化",
            "核准班級數": "1班",
            "每班核准人數": "20人",
            "每週總節(時)數": "2",
            "修業期限": "3個月",
            "招生對象": "國中"
        },
        {
            "核准科目名稱": "國文",
            "核准班級數": "1班",
            "每班核准人數": "20人",
            "每週總節(時)數": "2",
            "修業期限": "3個月",
            "招生對象": "國中"
        }
    ],
    "職員工": [
        "楊韓均",
        "葉亭萱",
        "曾慶昇",
        "王俞頴",
        "仇鈺潔"
    ]
}