{
    "負責人": [],
    "設立人": [],
    "班主任": [],
    "核准科目": [],
    "職員工": [
        "王增謙",
        "傅其輝",
        "王婌華",
        "黃怡嘉",
        "黃川益",
        "陳奕均",
        "黃琬情",
        "黃以人",
        "謝宜珊",
        "萬炳宏",
        "鄭晁易",
        "陳鈺涵",
        "潘意蕙",
        "林佳儒",
        "楊舜絜",
        "陳婉柔",
        "鄭愉樺",
        "吳宜修",
        "賴瑞妤",
        "蔡文心",
        "鄭雅純",
        "陳琬韻",
        "翁儀庭",
        "吳國生",
        "黃麗蓉",
        "陳嬑姵",
        "陳于梵",
        "徐慧華",
        "高慈云",
        "賴莼薇",
        "張櫻馨",
        "王文芸",
        "吳秋儀",
        "林奕均",
        "陳韻涵",
        "張以諾",
        "丁若倢"
    ]
}