{
    "補習班代碼": "20200811190429",
    "主管機關文件單位代碼": "6130",
    "補習班名稱": "臺北市私立中華棋道圍棋文理短期補習班",
    "補習班英文名稱": "",
    "補習班類別\/科目": "文理類,美術、書法、攝影、美工設計、圍棋類,",
    "地址": "大安區信義路3段202號4樓",
    "英文地址": "",
    "電話": "27071779",
    "立案情形": "已立案",
    "電話網類別": "",
    "電話網層別": "",
    "立案文號": "北市教社字第09733540400號",
    "廢止、註銷文號": "NULL",
    "立案日期": "2008-06-01",
    "廢止、註銷日期": "null",
    "傳真號碼": "",
    "電子郵件": "wenlinh57@gmail.com",
    "教室數": "3間",
    "飲用水設備維護管理": "接用自來水之固定飲用水設備",
    "教室面積": "69.74 平方公尺",
    "班舍總面積": "97.75平方公尺",
    "暫停招生文號": "",
    "暫停招生生效日": "",
    "暫停招生截止日": "",
    "負責人": [
        "許饒和"
    ],
    "設立人": [
        "許饒和"
    ],
    "班主任": [
        "黃文玲"
    ],
    "核准科目": [
        {
            "核准科目名稱": "圍棋",
            "核准班級數": "4班",
            "每班核准人數": "23人",
            "每週總節(時)數": "2",
            "修業期限": "5個月",
            "招生對象": "其他"
        },
        {
            "核准科目名稱": "數學",
            "核准班級數": "4班",
            "每班核准人數": "23人",
            "每週總節(時)數": "2",
            "修業期限": "5個月",
            "招生對象": "其他"
        },
        {
            "核准科目名稱": "國語",
            "核准班級數": "4班",
            "每班核准人數": "23人",
            "每週總節(時)數": "2",
            "修業期限": "5個月",
            "招生對象": "其他"
        },
        {
            "核准科目名稱": "自然與生活科技",
            "核准班級數": "4班",
            "每班核准人數": "23人",
            "每週總節(時)數": "2",
            "修業期限": "5個月",
            "招生對象": "其他"
        }
    ],
    "職員工": [
        "許美菊",
        "黃文玲",
        "林照雄",
        "黃文玲"
    ]
}