{
    "補習班代碼": "20200811180183",
    "主管機關文件單位代碼": "4017",
    "補習班名稱": "碧老師英文補習班",
    "補習班英文名稱": "",
    "補習班類別\/科目": "外語類,",
    "地址": "中山區北安路630巷25弄9號1樓",
    "英文地址": "",
    "電話": "(02)8509-8858",
    "立案情形": "已立案",
    "電話網類別": "",
    "電話網層別": "",
    "立案文號": "北市教六字第9028612100號",
    "廢止、註銷文號": "NULL",
    "立案日期": "2001-12-01",
    "廢止、註銷日期": "null",
    "傳真號碼": "",
    "電子郵件": "clairechiang1229@gmail.com",
    "教室數": "2間",
    "飲用水設備維護管理": "",
    "教室面積": "35.56 平方公尺",
    "班舍總面積": "71.0平方公尺",
    "暫停招生文號": "",
    "暫停招生生效日": "",
    "暫停招生截止日": "",
    "負責人": [
        "范姜復興"
    ],
    "設立人": [
        "范姜復興"
    ],
    "班主任": [
        "范姜閔"
    ],
    "核准科目": [
        {
            "核准科目名稱": "英文",
            "核准班級數": "2班",
            "每班核准人數": "29人",
            "每週總節(時)數": "",
            "修業期限": "個月",
            "招生對象": "學齡前"
        }
    ],
    "職員工": []
}