{
    "負責人": [],
    "設立人": [],
    "班主任": [],
    "核准科目": [],
    "職員工": [
        "陳佳儀",
        "余修瑄",
        "林詩倫",
        "郭映婕",
        "陳亭妤",
        "葉家妤",
        "侯允雯",
        "翁讓妙",
        "林雋瑒",
        "李佳慧",
        "廖琳玲",
        "林芯彤",
        "吳心妤",
        "李俊賢",
        "李雯惠",
        "陳柏宏",
        "段漢盈",
        "許麗珊",
        "陳宛妮",
        "劉姿妤",
        "簡蓓妤",
        "黃鼎元",
        "楊東霖",
        "林禹豪",
        "林書楷",
        "楊詠捷",
        "王品量",
        "蘇翊",
        "林沅宥",
        "胡育誠",
        "李少宸",
        "林裕宸"
    ]
}