{
    "補習班代碼": "20200811190330",
    "主管機關文件單位代碼": "6029",
    "補習班名稱": "臺北市私立聯誠電腦短期補習班",
    "補習班英文名稱": "",
    "補習班類別\/科目": "美術、書法、攝影、美工設計、圍棋類,",
    "地址": "中正區館前路2號5樓",
    "英文地址": "",
    "電話": "2389-6577",
    "立案情形": "已立案",
    "電話網類別": "",
    "電話網層別": "",
    "立案文號": "9730132900",
    "廢止、註銷文號": "",
    "立案日期": "2008-01-25",
    "廢止、註銷日期": "",
    "傳真號碼": "02-2388-4456",
    "電子郵件": "lc02.lccnet@gmail.com",
    "教室數": "6間",
    "飲用水設備維護管理": "",
    "教室面積": "251.46 平方公尺",
    "班舍總面積": "393.2平方公尺",
    "暫停招生文號": "",
    "暫停招生生效日": "",
    "暫停招生截止日": "",
    "負責人": [
        "曾家琦"
    ],
    "設立人": [
        "曾家琦"
    ],
    "班主任": [
        "曾家琦"
    ],
    "核准科目": [
        {
            "核准科目名稱": "電腦",
            "核准班級數": "5班",
            "每班核准人數": "23人",
            "每週總節(時)數": "2",
            "修業期限": "3個月",
            "招生對象": "其他"
        }
    ],
    "職員工": [
        "李永欽",
        "孫筱咪",
        "何秉修",
        "胡舜恩",
        "林秀娟",
        "徐瑋侖",
        "廖人頡",
        "陳姿帆",
        "陳泓學",
        "羅偉皓",
        "藍偉誠",
        "蔡杰叡",
        "楊澄竫",
        "彭碧珍",
        "郭宥昕",
        "楊智帆",
        "李易臻"
    ]
}