{
    "補習班代碼": "20200811180413",
    "主管機關文件單位代碼": "4255",
    "補習班名稱": "臺北市私立優兒音樂技藝短期補習班",
    "補習班英文名稱": "",
    "補習班類別\/科目": "美術、書法、攝影、美工設計、圍棋類,",
    "地址": "士林區天玉街38巷15號2樓",
    "英文地址": "",
    "電話": "28772200",
    "立案情形": "已立案",
    "電話網類別": "",
    "電話網層別": "",
    "立案文號": "北市教六字第09136305900號",
    "廢止、註銷文號": "NULL",
    "立案日期": "2002-09-01",
    "廢止、註銷日期": "null",
    "傳真號碼": "",
    "電子郵件": "",
    "教室數": "5間",
    "飲用水設備維護管理": "",
    "教室面積": "51.6025 平方公尺",
    "班舍總面積": "71.71平方公尺",
    "暫停招生文號": "",
    "暫停招生生效日": "",
    "暫停招生截止日": "",
    "負責人": [
        "蘇景鈴"
    ],
    "設立人": [
        "蘇景鈴"
    ],
    "班主任": [
        "林佑怡"
    ],
    "核准科目": [
        {
            "核准科目名稱": "美術",
            "核准班級數": "2班",
            "每班核准人數": "33人",
            "每週總節(時)數": "10",
            "修業期限": "6個月",
            "招生對象": "無限制"
        },
        {
            "核准科目名稱": "音樂",
            "核准班級數": "2班",
            "每班核准人數": "33人",
            "每週總節(時)數": "10",
            "修業期限": "6個月",
            "招生對象": "無限制"
        },
        {
            "核准科目名稱": "舞蹈",
            "核准班級數": "2班",
            "每班核准人數": "15人",
            "每週總節(時)數": "10",
            "修業期限": "個月",
            "招生對象": "無限制"
        }
    ],
    "職員工": []
}