{
    "負責人": [],
    "設立人": [],
    "班主任": [],
    "核准科目": [],
    "職員工": [
        "郭宥淇",
        "王翠蘭",
        "余若綺",
        "石莉文",
        "翁聿萱",
        "劉玥汝",
        "林麗瑜",
        "林齊盈",
        "馮純瑮",
        "徐逸軒",
        "張秀美",
        "楊聯芳",
        "黃義傑",
        "朱麗安",
        "朱菁弘",
        "鍾桂珠",
        "陳星文",
        "林雅歆",
        "張耀仁",
        "李美慧",
        "李宜珊",
        "葉冠廷",
        "林維儀",
        "游心如",
        "馬偉鈞",
        "林葦珊",
        "王俐文",
        "李高陽",
        "吳金雲",
        "林淵鐸",
        "許碧霜",
        "林嘉惠",
        "夏佩伶",
        "黃秋香",
        "葉雅婷",
        "張春琴",
        "歐芷筠",
        "吳淑寶",
        "張維憲",
        "王品雯",
        "王幼萍",
        "楊淑珍",
        "吳旻芳",
        "莊子萱",
        "呂鴻屏",
        "陳英織",
        "李宛琪",
        "楊子瑤",
        "楊季穎",
        "陳姵菱",
        "吳志仁",
        "張郁沛",
        "簡佩如",
        "林依穎",
        "杜嘉涓"
    ]
}