{
    "補習班代碼": "20200811181178",
    "主管機關文件單位代碼": "5030",
    "補習班名稱": "志光教育科技股份有限公司附設臺北市私立保成法律會計行政公職證照短期補習班",
    "補習班英文名稱": "",
    "補習班類別\/科目": "法政類,",
    "地址": "中正區館前路2號9樓",
    "英文地址": "",
    "電話": "23317517",
    "立案情形": "已立案",
    "電話網類別": "",
    "電話網層別": "",
    "立案文號": "北市教社字第09338175700號",
    "廢止、註銷文號": "NULL",
    "立案日期": "2004-11-01",
    "廢止、註銷日期": "null",
    "傳真號碼": "",
    "電子郵件": "",
    "教室數": "4間",
    "飲用水設備維護管理": "",
    "教室面積": "417.93 平方公尺",
    "班舍總面積": "808.244平方公尺",
    "暫停招生文號": "",
    "暫停招生生效日": "",
    "暫停招生截止日": "",
    "負責人": [
        "志光教育科技股份有限公司"
    ],
    "設立人": [
        "志光教育科技股份有限公司"
    ],
    "班主任": [
        "陳明男"
    ],
    "核准科目": [
        {
            "核准科目名稱": "行政",
            "核准班級數": "4班",
            "每班核准人數": "60人",
            "每週總節(時)數": "60",
            "修業期限": "6個月",
            "招生對象": "無限制"
        },
        {
            "核准科目名稱": "法律",
            "核准班級數": "4班",
            "每班核准人數": "60人",
            "每週總節(時)數": "60",
            "修業期限": "6個月",
            "招生對象": "無限制"
        },
        {
            "核准科目名稱": "會計",
            "核准班級數": "4班",
            "每班核准人數": "60人",
            "每週總節(時)數": "60",
            "修業期限": "6個月",
            "招生對象": "無限制"
        }
    ],
    "職員工": [
        "許祐嘉",
        "王毓豪",
        "孫立忠",
        "郭淑君",
        "平佳靈",
        "林昀萱",
        "賴怡宣",
        "許家寧",
        "簡于瑄",
        "林格葶",
        "洪振富",
        "劉盈吟",
        "陳明男",
        "葉伊修",
        "林靖智",
        "葉雅梅",
        "郭妍妤",
        "吳思萱",
        "何曉婷",
        "莊淑婷",
        "陳慈婷",
        "張家旗",
        "黃尚駿",
        "陳韋均",
        "陳俞均",
        "張秀瑤",
        "吳孟娟",
        "朱敏銑",
        "鄭亦詞",
        "潘晨瑋"
    ]
}