{
    "補習班代碼": "20200911060001",
    "主管機關文件單位代碼": "6439",
    "補習班名稱": "喜樂泉源股份有限公司附設臺北市私立希伯崙文理短期補習班敦化分班",
    "補習班英文名稱": "Private Short-Term Busiban",
    "補習班類別\/科目": "文理類,外語類,",
    "地址": "松山區敦化南路1段80巷42號1樓",
    "英文地址": "",
    "電話": "87710343",
    "立案情形": "已立案",
    "電話網類別": "",
    "電話網層別": "",
    "立案文號": "北市教社字第09837552700號",
    "廢止、註銷文號": "",
    "立案日期": "2009-11-01",
    "廢止、註銷日期": "",
    "傳真號碼": "",
    "電子郵件": "eric_hsu@liveabc.com",
    "教室數": "4間",
    "飲用水設備維護管理": "",
    "教室面積": "60.62 平方公尺",
    "班舍總面積": "101.89平方公尺",
    "暫停招生文號": "",
    "暫停招生生效日": "",
    "暫停招生截止日": "",
    "負責人": [
        "喜樂泉源股份有限公司"
    ],
    "設立人": [
        "喜樂泉源股份有限公司"
    ],
    "班主任": [
        "寇亞容"
    ],
    "核准科目": [
        {
            "核准科目名稱": "英文",
            "核准班級數": "3班",
            "每班核准人數": "46人",
            "每週總節(時)數": "20",
            "修業期限": "3個月",
            "招生對象": "國小"
        },
        {
            "核准科目名稱": "數學",
            "核准班級數": "3班",
            "每班核准人數": "46人",
            "每週總節(時)數": "20",
            "修業期限": "3個月",
            "招生對象": "國小"
        },
        {
            "核准科目名稱": "國語",
            "核准班級數": "3班",
            "每班核准人數": "46人",
            "每週總節(時)數": "20",
            "修業期限": "3個月",
            "招生對象": "國小"
        },
        {
            "核准科目名稱": "自然與生活科技",
            "核准班級數": "3班",
            "每班核准人數": "46人",
            "每週總節(時)數": "20",
            "修業期限": "3個月",
            "招生對象": "國小"
        }
    ],
    "職員工": []
}