{
    "補習班代碼": "20200811181214",
    "主管機關文件單位代碼": "5066",
    "補習班名稱": "臺北巿私立教育家文理短期補習班",
    "補習班英文名稱": "",
    "補習班類別\/科目": "文理類,",
    "地址": "中正區博愛路53號6樓",
    "英文地址": "",
    "電話": "23816818",
    "立案情形": "已立案",
    "電話網類別": "",
    "電話網層別": "",
    "立案文號": "9339150000",
    "廢止、註銷文號": "NULL",
    "立案日期": "2004-11-17",
    "廢止、註銷日期": "null",
    "傳真號碼": "",
    "電子郵件": "educatorcustomerservice@gmail.com",
    "教室數": "2間",
    "飲用水設備維護管理": "",
    "教室面積": "170.09 平方公尺",
    "班舍總面積": "172.79平方公尺",
    "暫停招生文號": "",
    "暫停招生生效日": "",
    "暫停招生截止日": "",
    "負責人": [
        "彭鐘穎"
    ],
    "設立人": [
        "彭鐘穎"
    ],
    "班主任": [
        "彭鐘穎"
    ],
    "核准科目": [
        {
            "核准科目名稱": "英文",
            "核准班級數": "2班",
            "每班核准人數": "60人",
            "每週總節(時)數": "2",
            "修業期限": "5個月",
            "招生對象": "其他"
        },
        {
            "核准科目名稱": "社會學科",
            "核准班級數": "2班",
            "每班核准人數": "60人",
            "每週總節(時)數": "2",
            "修業期限": "5個月",
            "招生對象": "其他"
        },
        {
            "核准科目名稱": "國文",
            "核准班級數": "2班",
            "每班核准人數": "60人",
            "每週總節(時)數": "2",
            "修業期限": "5個月",
            "招生對象": "其他"
        },
        {
            "核准科目名稱": "教育心理學科",
            "核准班級數": "2班",
            "每班核准人數": "60人",
            "每週總節(時)數": "2",
            "修業期限": "5個月",
            "招生對象": "其他"
        }
    ],
    "職員工": [
        "吳承蔚",
        "彭鐘穎",
        "蔡佳佩",
        "蔡旿霖",
        "蔡怡宣",
        "柯筠育",
        "黃育佳",
        "陳郁涵"
    ]
}