{
    "負責人": [],
    "設立人": [],
    "班主任": [],
    "核准科目": [],
    "職員工": [
        "林佳璇",
        "傅彥庭",
        "江怡蕙",
        "王盈惠",
        "陳玲君",
        "江晏華",
        "劉思妤",
        "梁育誠",
        "張宜茵",
        "廖信宇",
        "鄧維萱",
        "郭栢睿",
        "劉嘉媁",
        "汪薇安",
        "黃思婷",
        "陳麗如",
        "王家誠",
        "胡敬",
        "吳佩綺",
        "王品方",
        "黃于玲",
        "李俞潔",
        "金佳弘",
        "王玉如",
        "林品賢",
        "柯奕豪",
        "王之函",
        "李侑璇",
        "蕭宏",
        "徐永光",
        "陳宥諼",
        "劉璧慧",
        "李昆翰",
        "王俊彬",
        "廖珮如",
        "李雅雯",
        "王傳勛",
        "王薏涵",
        "林家弘"
    ]
}