{
    "補習班代碼": "20202103300004",
    "主管機關文件單位代碼": "8045",
    "補習班名稱": "赫紀電腦有限公司附設臺北市私立赫紀電腦技藝短期補習班",
    "補習班英文名稱": "Private Short-Term Busiban",
    "補習班類別\/科目": "資訊類,",
    "地址": "中正區南陽街13號7樓",
    "英文地址": "",
    "電話": "(02)2370-2999",
    "立案情形": "已立案",
    "電話網類別": "",
    "電話網層別": "X-X-X",
    "立案文號": "北市教終字第1103005419號",
    "廢止、註銷文號": "",
    "立案日期": "2021-03-30",
    "廢止、註銷日期": "",
    "傳真號碼": "(02)",
    "電子郵件": "rius1281@appedu.com.tw",
    "教室數": "3間",
    "飲用水設備維護管理": "接用自來水之固定飲用水設備",
    "教室面積": "69.42 平方公尺",
    "班舍總面積": "181.84平方公尺",
    "暫停招生文號": "",
    "暫停招生生效日": "",
    "暫停招生截止日": "",
    "負責人": [
        "赫紀電腦有限公司(負責人：林佑亭)"
    ],
    "設立人": [
        "赫紀電腦有限公司(負責人：林佑亭)"
    ],
    "班主任": [
        "丁貴慈"
    ],
    "核准科目": [
        {
            "核准科目名稱": "電腦",
            "核准班級數": "3班",
            "每班核准人數": "49人",
            "每週總節(時)數": "6",
            "修業期限": "5個月",
            "招生對象": "無限制"
        }
    ],
    "職員工": [
        "郭韋德",
        "陳珮君",
        "陳郁霖",
        "呂冠頴",
        "陳莉玲",
        "陳文婕",
        "李嘉敏",
        "傅苑菱",
        "吳羽晴",
        "張雅柔",
        "林佑亭",
        "薛雯文",
        "翁瑜翔",
        "盧宥希",
        "林庭",
        "鄭宇庭",
        "周衍廷",
        "陳詩云",
        "侯淳翊",
        "柯亭宇",
        "黃金玉",
        "張德凱",
        "李昀庭",
        "楊馥瑄",
        "徐誠遠"
    ]
}