{
    "補習班代碼": "20200811180169",
    "主管機關文件單位代碼": "4003",
    "補習班名稱": "臺北市私立立功文理短期補習班",
    "補習班英文名稱": "",
    "補習班類別\/科目": "文理類,",
    "地址": "大安區光復南路412號2樓之1",
    "英文地址": "",
    "電話": "27083929",
    "立案情形": "已立案",
    "電話網類別": "",
    "電話網層別": "",
    "立案文號": "9028454300",
    "廢止、註銷文號": "NULL",
    "立案日期": "2001-11-01",
    "廢止、註銷日期": "null",
    "傳真號碼": "27083930",
    "電子郵件": "ligon27083929@gmail.com",
    "教室數": "3間",
    "飲用水設備維護管理": "",
    "教室面積": "79.21 平方公尺",
    "班舍總面積": "107.21平方公尺",
    "暫停招生文號": "",
    "暫停招生生效日": "",
    "暫停招生截止日": "",
    "負責人": [
        "鄭佩莉"
    ],
    "設立人": [
        "鄭佩莉"
    ],
    "班主任": [
        "陳立偉"
    ],
    "核准科目": [
        {
            "核准科目名稱": "英文",
            "核准班級數": "3班",
            "每班核准人數": "60人",
            "每週總節(時)數": "",
            "修業期限": "個月",
            "招生對象": "學齡前"
        },
        {
            "核准科目名稱": "數學",
            "核准班級數": "3班",
            "每班核准人數": "60人",
            "每週總節(時)數": "",
            "修業期限": "個月",
            "招生對象": "學齡前"
        },
        {
            "核准科目名稱": "理化",
            "核准班級數": "3班",
            "每班核准人數": "60人",
            "每週總節(時)數": "",
            "修業期限": "個月",
            "招生對象": "學齡前"
        }
    ],
    "職員工": [
        "劉品言",
        "簡秋華",
        "高煥承",
        "林俊彥",
        "陳靖文"
    ]
}