{
    "補習班代碼": "20201703140382",
    "主管機關文件單位代碼": "6812",
    "補習班名稱": "誠功語文補習班",
    "補習班英文名稱": "",
    "補習班類別\/科目": "外語類,",
    "地址": "內湖區成功路4段61巷28號1樓及地下1樓",
    "英文地址": "",
    "電話": "87921515",
    "立案情形": "已立案",
    "電話網類別": "",
    "電話網層別": "",
    "立案文號": "北市教社字第10035306800號",
    "廢止、註銷文號": "",
    "立案日期": "2011-06-01",
    "廢止、註銷日期": "",
    "傳真號碼": "27945600",
    "電子郵件": "chs21118@gmail.com",
    "教室數": "3間",
    "飲用水設備維護管理": "學生自行準備飲用水",
    "教室面積": "79.95 平方公尺",
    "班舍總面積": "138.49平方公尺",
    "暫停招生文號": "",
    "暫停招生生效日": "",
    "暫停招生截止日": "",
    "負責人": [
        "紀怡嫻"
    ],
    "設立人": [
        "紀怡嫻"
    ],
    "班主任": [
        "紀怡嫻"
    ],
    "核准科目": [
        {
            "核准科目名稱": "國語",
            "核准班級數": "3班",
            "每班核准人數": "45人",
            "每週總節(時)數": "20",
            "修業期限": "5個月",
            "招生對象": "國小"
        },
        {
            "核准科目名稱": "美語",
            "核准班級數": "3班",
            "每班核准人數": "45人",
            "每週總節(時)數": "20",
            "修業期限": "5個月",
            "招生對象": "國小"
        }
    ],
    "職員工": [
        "林日愉",
        "楊仕浠",
        "紀淑嫻"
    ]
}