{
    "補習班代碼": "52200412090003",
    "主管機關文件單位代碼": "",
    "補習班名稱": "嘉義市私立領航家文理短期補習班",
    "補習班英文名稱": "Private Navigater Short-Term Busiban",
    "補習班類別\/科目": "文理類,",
    "地址": "600035嘉義市東區頂寮里芳德街90號(1-3樓)",
    "英文地址": "1-3F., No. 90, Fangde St., East Dist., Chiayi City",
    "電話": "(05)2236803",
    "立案情形": "已立案",
    "電話網類別": "",
    "電話網層別": "X-X-X",
    "立案文號": "府教社字第0930116586 號",
    "廢止、註銷文號": "",
    "立案日期": "2004-12-01",
    "廢止、註銷日期": "",
    "傳真號碼": "(05)",
    "電子郵件": "",
    "教室數": "1間",
    "飲用水設備維護管理": "",
    "教室面積": "84.0 平方公尺",
    "班舍總面積": "128.1平方公尺",
    "暫停招生文號": "府教社字第 號",
    "暫停招生生效日": "",
    "暫停招生截止日": "",
    "負責人": [
        "余姝瑩"
    ],
    "設立人": [
        "余姝瑩"
    ],
    "班主任": [
        "余姝瑩"
    ],
    "核准科目": [
        {
            "核准科目名稱": "英文",
            "核准班級數": "2班",
            "每班核准人數": "20人",
            "每週總節(時)數": "12",
            "修業期限": "3個月",
            "招生對象": "國小"
        }
    ],
    "職員工": []
}