{
    "補習班代碼": "33200612210011",
    "主管機關文件單位代碼": "",
    "補習班名稱": "私立頂龍美語文理短期補習班",
    "補習班英文名稱": "Private Short-Term Busiban",
    "補習班類別\/科目": "文理類,外語類,",
    "地址": "龍潭區龍祥村干城路188號2-4樓",
    "英文地址": "",
    "電話": "(03)4803895",
    "立案情形": "已立案",
    "電話網類別": "",
    "電話網層別": "X-X-X",
    "立案文號": "府教社字第 0950165550號",
    "廢止、註銷文號": "",
    "立案日期": "2006-06-14",
    "廢止、註銷日期": "",
    "傳真號碼": "",
    "電子郵件": "0934000769@top-edu.com.tw",
    "教室數": "4間",
    "飲用水設備維護管理": "學生自行準備飲用水",
    "教室面積": "136.25 平方公尺",
    "班舍總面積": "456.81平方公尺",
    "暫停招生文號": "",
    "暫停招生生效日": "",
    "暫停招生截止日": "",
    "負責人": [
        "范國華"
    ],
    "設立人": [
        "范國華"
    ],
    "班主任": [
        "蔡明錡"
    ],
    "核准科目": [
        {
            "核准科目名稱": "國一英數理班",
            "核准班級數": "1班",
            "每班核准人數": "28人",
            "每週總節(時)數": "6",
            "修業期限": "5個月",
            "招生對象": "國中"
        },
        {
            "核准科目名稱": "國三英數理班",
            "核准班級數": "1班",
            "每班核准人數": "38人",
            "每週總節(時)數": "9",
            "修業期限": "5個月",
            "招生對象": "國中"
        },
        {
            "核准科目名稱": "兒童美語",
            "核准班級數": "1班",
            "每班核准人數": "29人",
            "每週總節(時)數": "4",
            "修業期限": "5個月",
            "招生對象": "國小"
        },
        {
            "核准科目名稱": "國二英數理班",
            "核准班級數": "1班",
            "每班核准人數": "28人",
            "每週總節(時)數": "9",
            "修業期限": "5個月",
            "招生對象": "國中"
        }
    ],
    "職員工": []
}